ifdtools/__init__.py
ifdtools/config_class/__init__.py
ifdtools/config_class/config_class.py
ifdtools/cvr_api/__init__.py
ifdtools/cvr_api/cvr_regnskab_class.py
ifdtools/cvr_api/cvr_response_class.py
ifdtools/cvr_api/cvr_response_owner_class.py
ifdtools/cvr_api/cvrapi_functions/__init__.py
ifdtools/cvr_api/cvrapi_functions/name_handler.py
ifdtools/cvr_api/main.py
ifdtools/cvr_api/main_old.py
ifdtools/cvr_api/nace_map/__init__.py
ifdtools/cvr_api/nace_map/db25_til_db7.py
ifdtools/cvr_api/nace_map/nace_koder_map.py
ifdtools/cvr_api/xbrl/ressources/fsa/fsa.xsd
ifdtools/cvr_api/xbrl/ressources/fsa/fsa_labels.xml
ifdtools/cvr_api/xbrl/ressources/fsa/fsa_translations.xlsx
ifdtools/cvr_api/xbrl/ressources/general/general_translations.xlsx
ifdtools/cvr_api/xbrl/ressources/ifrs/ifrs_translations.xlsx
ifdtools/cvr_api/xbrl/taxonomy_class.py
ifdtools/db_helper/__init__.py
ifdtools/db_helper/dbh_class_def.py
ifdtools-0.2.6.dist-info/METADATA
ifdtools-0.2.6.dist-info/WHEEL
ifdtools-0.2.6.dist-info/RECORD
