Metadata-Version: 2.1
Name: ifdtools
Version: 0.2.6
Summary: 
Author: Your Name
Author-email: you@example.com
Requires-Python: ==3.12.2
Classifier: Programming Language :: Python :: 3
Requires-Dist: ipykernel (>=6.29.4,<7.0.0)
Requires-Dist: keyring (>=25.2.1,<26.0.0)
Requires-Dist: lxml (>=5.2.2,<6.0.0)
Requires-Dist: openpyxl (>=3.1.5,<4.0.0)
Requires-Dist: pandas (>=2.2.2,<3.0.0)
Requires-Dist: pymssql (>=2.3.1,<3.0.0)
Requires-Dist: pyodbc (>=5.1.0,<6.0.0)
Requires-Dist: requests (>=2.32.3,<3.0.0)
Requires-Dist: sqlalchemy (>=2.0.30,<3.0.0)
Requires-Dist: tqdm (>=4.66.4,<5.0.0)
Requires-Dist: xmltodict (>=0.13.0,<0.14.0)
